SeisMonitor/__init__.py
SeisMonitor/utils.py
SeisMonitor/utils4examples.py
SeisMonitor/core/__init__.py
SeisMonitor/core/client.py
SeisMonitor/core/objects.py
SeisMonitor/core/utils.py
SeisMonitor/monitor/__init__.py
SeisMonitor/monitor/seismonitor.py
SeisMonitor/monitor/associator/__init__.py
SeisMonitor/monitor/associator/ai.py
SeisMonitor/monitor/associator/utils.py
SeisMonitor/monitor/downloader/__init__.py
SeisMonitor/monitor/downloader/obspy_mdl.py
SeisMonitor/monitor/downloader/seismonitor.py
SeisMonitor/monitor/downloader/utils.py
SeisMonitor/monitor/locator/__init__.py
SeisMonitor/monitor/locator/utils.py
SeisMonitor/monitor/locator/hypoDD/__init__.py
SeisMonitor/monitor/locator/hypoDD/core.py
SeisMonitor/monitor/locator/hypoDD/utils.py
SeisMonitor/monitor/locator/hypocenter/__init__.py
SeisMonitor/monitor/locator/hypocenter/core.py
SeisMonitor/monitor/locator/hypocenter/utils.py
SeisMonitor/monitor/locator/nlloc/__init__.py
SeisMonitor/monitor/locator/nlloc/nlloc.py
SeisMonitor/monitor/locator/nlloc/utils.py
SeisMonitor/monitor/magnitude/__init__.py
SeisMonitor/monitor/magnitude/mag.py
SeisMonitor/monitor/magnitude/utils.py
SeisMonitor/monitor/picker/__init__.py
SeisMonitor/monitor/picker/ai.py
SeisMonitor/monitor/picker/utils.py
SeisMonitor/plot/__init__.py
SeisMonitor/plot/picks.py
SeisMonitor/plot/utils.py
seismonitor-0.0.58.dist-info/LICENSE
seismonitor-0.0.58.dist-info/METADATA
seismonitor-0.0.58.dist-info/WHEEL
seismonitor-0.0.58.dist-info/top_level.txt
seismonitor-0.0.58.dist-info/RECORD
